README.md
setup.cfg
setup.py
peercoin_rpc/__init__.py
peercoin_rpc/peercoin_rpc.py
peercoin_rpc.egg-info/PKG-INFO
peercoin_rpc.egg-info/SOURCES.txt
peercoin_rpc.egg-info/dependency_links.txt
peercoin_rpc.egg-info/requires.txt
peercoin_rpc.egg-info/top_level.txt