Metadata-Version: 2.1
Name: peercoin-rpc
Version: 0.61
Summary: Library to communicate with peercoin daemon via JSON-RPC protocol.
Home-page: https://github.com/peercoin/peercoin_rpc
Author: Peerchemist
Author-email: peerchemist@protonmail.ch
License: MIT
Keywords: peercoin,json-rpc,cryptocurrency,blockchain
Platform: any
Classifier: Development Status :: 4 - Beta
Classifier: Intended Audience :: Financial and Insurance Industry
Classifier: Programming Language :: Python
Classifier: Operating System :: OS Independent
Classifier: Natural Language :: English
Classifier: License :: OSI Approved :: MIT License
